{
  "data": {
    "article": {},
    "attachments": {},
    "author_id": "1722693102367039488",
    "conversation_id": "2042044205393178720",
    "created_at": "2026-04-09T14:47:02.000Z",
    "edit_controls": {
      "editable_until": "2026-04-09T15:47:02.000Z",
      "edits_remaining": 5,
      "is_edit_eligible": false
    },
    "edit_history_tweet_ids": [
      "2042252954082906479"
    ],
    "entities": {
      "mentions": [
        {
          "end": 16,
          "id": "1451855512002170884",
          "start": 0,
          "username": "7lIRHt7PWA43lqo"
        }
      ]
    },
    "geo": {},
    "id": "2042252954082906479",
    "in_reply_to_user_id": "1451855512002170884",
    "lang": "zh",
    "note_tweet": {
      "entities": {}
    },
    "possibly_sensitive": false,
    "public_metrics": {
      "bookmark_count": 0,
      "impression_count": 0,
      "like_count": 0,
      "quote_count": 0,
      "reply_count": 0,
      "retweet_count": 0
    },
    "referenced_tweets": [
      {
        "id": "2042252002768613580",
        "type": "replied_to"
      }
    ],
    "reply_settings": "everyone",
    "text": "@7lIRHt7PWA43lqo 身边有很多人就不可能有安全感"
  },
  "includes": {
    "tweets": [
      {
        "article": {},
        "attachments": {},
        "author_id": "1722693102367039488",
        "conversation_id": "2042044205393178720",
        "created_at": "2026-04-09T14:47:02.000Z",
        "edit_controls": {
          "editable_until": "2026-04-09T15:47:02.000Z",
          "edits_remaining": 5,
          "is_edit_eligible": false
        },
        "edit_history_tweet_ids": [
          "2042252954082906479"
        ],
        "entities": {
          "mentions": [
            {
              "end": 16,
              "id": "1451855512002170884",
              "start": 0,
              "username": "7lIRHt7PWA43lqo"
            }
          ]
        },
        "geo": {},
        "id": "2042252954082906479",
        "in_reply_to_user_id": "1451855512002170884",
        "lang": "zh",
        "note_tweet": {
          "entities": {}
        },
        "possibly_sensitive": false,
        "public_metrics": {
          "bookmark_count": 0,
          "impression_count": 0,
          "like_count": 0,
          "quote_count": 0,
          "reply_count": 0,
          "retweet_count": 0
        },
        "referenced_tweets": [
          {
            "id": "2042252002768613580",
            "type": "replied_to"
          }
        ],
        "reply_settings": "everyone",
        "text": "@7lIRHt7PWA43lqo 身边有很多人就不可能有安全感"
      },
      {
        "article": {},
        "attachments": {},
        "author_id": "1451855512002170884",
        "conversation_id": "2042044205393178720",
        "created_at": "2026-04-09T14:43:15.000Z",
        "edit_controls": {
          "editable_until": "2026-04-09T15:43:15.000Z",
          "edits_remaining": 5,
          "is_edit_eligible": false
        },
        "edit_history_tweet_ids": [
          "2042252002768613580"
        ],
        "entities": {
          "mentions": [
            {
              "end": 15,
              "id": "1722693102367039488",
              "start": 0,
              "username": "kong_lian53017"
            }
          ]
        },
        "geo": {},
        "id": "2042252002768613580",
        "in_reply_to_user_id": "1722693102367039488",
        "lang": "zh",
        "note_tweet": {
          "entities": {}
        },
        "possibly_sensitive": false,
        "public_metrics": {
          "bookmark_count": 0,
          "impression_count": 3,
          "like_count": 1,
          "quote_count": 0,
          "reply_count": 1,
          "retweet_count": 0
        },
        "referenced_tweets": [
          {
            "id": "2042044205393178720",
            "type": "replied_to"
          }
        ],
        "reply_settings": "everyone",
        "text": "@kong_lian53017 但是如果他对你与众不同 给足你安全感又是另外一种更加强烈的幸福了"
      }
    ],
    "users": [
      {
        "created_at": "2023-11-09T19:10:42.000Z",
        "description": "我的生命也能如烟花般绚烂吗｜00年INFJ｜主页充斥无意义日常碎碎念｜精神状态不稳定间歇性发疯｜会查主页，互fo随缘",
        "id": "1722693102367039488",
        "location": "一颗星",
        "name": "空恋",
        "pinned_tweet_id": "2036676205458632900",
        "profile_image_url": "https://pbs.twimg.com/profile_images/1870808614358966272/yjU8OVI2_normal.jpg",
        "protected": false,
        "public_metrics": {
          "followers_count": 143,
          "following_count": 86,
          "like_count": 3811,
          "listed_count": 0,
          "media_count": 16,
          "tweet_count": 1643
        },
        "username": "kong_lian53017",
        "verified": false
      },
      {
        "created_at": "2021-10-23T10:18:32.000Z",
        "description": "偶尔刷推",
        "id": "1451855512002170884",
        "name": "Kaze",
        "profile_image_url": "https://pbs.twimg.com/profile_images/2024825822490841088/82e7fD7x_normal.jpg",
        "protected": false,
        "public_metrics": {
          "followers_count": 2,
          "following_count": 93,
          "like_count": 120,
          "listed_count": 0,
          "media_count": 0,
          "tweet_count": 50
        },
        "username": "7lIRHt7PWA43lqo",
        "verified": false
      }
    ]
  }
}