{
  "data": {
    "article": {},
    "attachments": {},
    "author_id": "1722693102367039488",
    "conversation_id": "2039203461607444650",
    "created_at": "2026-04-01T04:49:26.000Z",
    "edit_controls": {
      "editable_until": "2026-04-01T05:49:26.000Z",
      "edits_remaining": 5,
      "is_edit_eligible": false
    },
    "edit_history_tweet_ids": [
      "2039203461607444650"
    ],
    "entities": {
      "mentions": [
        {
          "end": 19,
          "id": "1512373779933978626",
          "start": 3,
          "username": "sweetiekittylol"
        }
      ]
    },
    "geo": {},
    "id": "2039203461607444650",
    "lang": "zh",
    "note_tweet": {
      "entities": {}
    },
    "possibly_sensitive": false,
    "public_metrics": {
      "bookmark_count": 0,
      "impression_count": 0,
      "like_count": 0,
      "quote_count": 0,
      "reply_count": 0,
      "retweet_count": 2
    },
    "referenced_tweets": [
      {
        "id": "2039184863006511375",
        "type": "retweeted"
      }
    ],
    "reply_settings": "everyone",
    "text": "RT @sweetiekittylol: 你为什么连骗骗我都不肯？"
  },
  "includes": {
    "tweets": [
      {
        "article": {},
        "attachments": {},
        "author_id": "1722693102367039488",
        "conversation_id": "2039203461607444650",
        "created_at": "2026-04-01T04:49:26.000Z",
        "edit_controls": {
          "editable_until": "2026-04-01T05:49:26.000Z",
          "edits_remaining": 5,
          "is_edit_eligible": false
        },
        "edit_history_tweet_ids": [
          "2039203461607444650"
        ],
        "entities": {
          "mentions": [
            {
              "end": 19,
              "id": "1512373779933978626",
              "start": 3,
              "username": "sweetiekittylol"
            }
          ]
        },
        "geo": {},
        "id": "2039203461607444650",
        "lang": "zh",
        "note_tweet": {
          "entities": {}
        },
        "possibly_sensitive": false,
        "public_metrics": {
          "bookmark_count": 0,
          "impression_count": 0,
          "like_count": 0,
          "quote_count": 0,
          "reply_count": 0,
          "retweet_count": 2
        },
        "referenced_tweets": [
          {
            "id": "2039184863006511375",
            "type": "retweeted"
          }
        ],
        "reply_settings": "everyone",
        "text": "RT @sweetiekittylol: 你为什么连骗骗我都不肯？"
      },
      {
        "article": {},
        "attachments": {},
        "author_id": "1512373779933978626",
        "conversation_id": "2039184863006511375",
        "created_at": "2026-04-01T03:35:32.000Z",
        "edit_controls": {
          "editable_until": "2026-04-01T04:35:32.000Z",
          "edits_remaining": 5,
          "is_edit_eligible": true
        },
        "edit_history_tweet_ids": [
          "2039184863006511375"
        ],
        "entities": {},
        "geo": {},
        "id": "2039184863006511375",
        "lang": "zh",
        "note_tweet": {
          "entities": {}
        },
        "possibly_sensitive": false,
        "public_metrics": {
          "bookmark_count": 0,
          "impression_count": 115,
          "like_count": 3,
          "quote_count": 0,
          "reply_count": 0,
          "retweet_count": 2
        },
        "reply_settings": "everyone",
        "text": "你为什么连骗骗我都不肯？"
      }
    ],
    "users": [
      {
        "created_at": "2023-11-09T19:10:42.000Z",
        "description": "我的生命也能如烟花般绚烂吗｜00年INFJ｜主页充斥无意义日常碎碎念｜精神状态不稳定间歇性发疯｜女孩请跟我互关聊天扩列",
        "id": "1722693102367039488",
        "location": "一颗星",
        "name": "空恋",
        "pinned_tweet_id": "2036676205458632900",
        "profile_image_url": "https://pbs.twimg.com/profile_images/1870808614358966272/yjU8OVI2_normal.jpg",
        "protected": false,
        "public_metrics": {
          "followers_count": 100,
          "following_count": 70,
          "like_count": 1923,
          "listed_count": 0,
          "media_count": 11,
          "tweet_count": 869
        },
        "username": "kong_lian53017",
        "verified": false
      },
      {
        "created_at": "2022-04-08T10:16:35.000Z",
        "description": "ᐕ)ﾉ@kissmyloin",
        "entities": {
          "description": {
            "mentions": [
              {
                "end": 14,
                "start": 3,
                "username": "kissmyloin"
              }
            ]
          }
        },
        "id": "1512373779933978626",
        "location": "小猫会永远陪在你身边",
        "name": "有时变成你下班路上遇见的小猫",
        "pinned_tweet_id": "1996192099121963469",
        "profile_image_url": "https://pbs.twimg.com/profile_images/1774994951652376576/zBfhfO-u_normal.jpg",
        "protected": false,
        "public_metrics": {
          "followers_count": 23676,
          "following_count": 666,
          "like_count": 14731,
          "listed_count": 55,
          "media_count": 1121,
          "tweet_count": 9189
        },
        "username": "sweetiekittylol",
        "verified": false
      }
    ]
  }
}