{
  "data": {
    "article": {},
    "attachments": {},
    "author_id": "1722693102367039488",
    "conversation_id": "2056203730748387820",
    "created_at": "2026-05-18T02:44:08.000Z",
    "edit_controls": {
      "editable_until": "2026-05-18T03:44:08.000Z",
      "edits_remaining": 5,
      "is_edit_eligible": false
    },
    "edit_history_tweet_ids": [
      "2056204160530559152"
    ],
    "entities": {
      "mentions": [
        {
          "end": 11,
          "id": "1613926971658108930",
          "start": 0,
          "username": "xx95944623"
        }
      ]
    },
    "geo": {},
    "id": "2056204160530559152",
    "in_reply_to_user_id": "1613926971658108930",
    "lang": "zh",
    "note_tweet": {
      "entities": {}
    },
    "possibly_sensitive": false,
    "public_metrics": {
      "bookmark_count": 0,
      "impression_count": 0,
      "like_count": 0,
      "quote_count": 0,
      "reply_count": 0,
      "retweet_count": 0
    },
    "referenced_tweets": [
      {
        "id": "2056203730748387820",
        "type": "replied_to"
      }
    ],
    "reply_settings": "everyone",
    "text": "@xx95944623 啊啊啊好尴尬"
  },
  "includes": {
    "tweets": [
      {
        "article": {},
        "attachments": {},
        "author_id": "1722693102367039488",
        "conversation_id": "2056203730748387820",
        "created_at": "2026-05-18T02:44:08.000Z",
        "edit_controls": {
          "editable_until": "2026-05-18T03:44:08.000Z",
          "edits_remaining": 5,
          "is_edit_eligible": false
        },
        "edit_history_tweet_ids": [
          "2056204160530559152"
        ],
        "entities": {
          "mentions": [
            {
              "end": 11,
              "id": "1613926971658108930",
              "start": 0,
              "username": "xx95944623"
            }
          ]
        },
        "geo": {},
        "id": "2056204160530559152",
        "in_reply_to_user_id": "1613926971658108930",
        "lang": "zh",
        "note_tweet": {
          "entities": {}
        },
        "possibly_sensitive": false,
        "public_metrics": {
          "bookmark_count": 0,
          "impression_count": 0,
          "like_count": 0,
          "quote_count": 0,
          "reply_count": 0,
          "retweet_count": 0
        },
        "referenced_tweets": [
          {
            "id": "2056203730748387820",
            "type": "replied_to"
          }
        ],
        "reply_settings": "everyone",
        "text": "@xx95944623 啊啊啊好尴尬"
      },
      {
        "article": {},
        "attachments": {},
        "author_id": "1613926971658108930",
        "conversation_id": "2056203730748387820",
        "created_at": "2026-05-18T02:42:26.000Z",
        "edit_controls": {
          "editable_until": "2026-05-18T03:42:26.000Z",
          "edits_remaining": 5,
          "is_edit_eligible": true
        },
        "edit_history_tweet_ids": [
          "2056203730748387820"
        ],
        "entities": {},
        "geo": {},
        "id": "2056203730748387820",
        "lang": "zh",
        "note_tweet": {
          "entities": {}
        },
        "possibly_sensitive": false,
        "public_metrics": {
          "bookmark_count": 0,
          "impression_count": 1,
          "like_count": 1,
          "quote_count": 0,
          "reply_count": 1,
          "retweet_count": 0
        },
        "reply_settings": "everyone",
        "text": "我没惹，我在视奸关注我的人的主页，全是片，然后老师像鬼一样出现在了我跟我朋友旁边😇"
      }
    ],
    "users": [
      {
        "created_at": "2023-11-09T19:10:42.000Z",
        "description": "我的生命也能如烟花般绚烂吗｜00年INFJ｜主页充斥无意义日常碎碎念和负能｜精神状态不稳定间歇性发疯｜会查主页，互fo只互感兴趣的｜匿名：https://t.co/OkTldu1tmL｜赞赏码在置顶评论，感谢喜欢感谢投喂~",
        "entities": {
          "description": {
            "urls": [
              {
                "display_url": "ngl.link/kong_lian",
                "end": 92,
                "expanded_url": "https://ngl.link/kong_lian",
                "start": 69,
                "url": "https://t.co/OkTldu1tmL"
              }
            ]
          }
        },
        "id": "1722693102367039488",
        "location": "一颗星",
        "name": "空恋",
        "pinned_tweet_id": "2036676205458632900",
        "profile_image_url": "https://pbs.twimg.com/profile_images/1870808614358966272/yjU8OVI2_normal.jpg",
        "protected": false,
        "public_metrics": {
          "followers_count": 312,
          "following_count": 113,
          "like_count": 15642,
          "listed_count": 0,
          "media_count": 81,
          "tweet_count": 5328
        },
        "username": "kong_lian53017",
        "verified": false
      },
      {
        "created_at": "2023-01-13T15:52:45.000Z",
        "description": "高敏回避INFP/碎碎念日记📓\n人就像一个洋葱，切下来每一片都让人落泪",
        "id": "1613926971658108930",
        "location": "眠眠羊的小世界",
        "name": "眠眠羊",
        "pinned_tweet_id": "2054825271237488669",
        "profile_image_url": "https://pbs.twimg.com/profile_images/2037088683237793792/qU3yJ-pW_normal.jpg",
        "protected": false,
        "public_metrics": {
          "followers_count": 99,
          "following_count": 38,
          "like_count": 845,
          "listed_count": 0,
          "media_count": 118,
          "tweet_count": 873
        },
        "username": "xx95944623",
        "verified": false
      }
    ]
  }
}