{
  "data": {
    "article": {},
    "attachments": {},
    "author_id": "1722693102367039488",
    "conversation_id": "2033558959454670990",
    "created_at": "2026-03-16T15:05:11.000Z",
    "edit_controls": {
      "editable_until": "2026-03-16T16:05:11.000Z",
      "edits_remaining": 5,
      "is_edit_eligible": false
    },
    "edit_history_tweet_ids": [
      "2033560213702496369"
    ],
    "entities": {
      "mentions": [
        {
          "end": 10,
          "id": "2032066678822260736",
          "start": 0,
          "username": "redeemkkk"
        }
      ]
    },
    "geo": {},
    "id": "2033560213702496369",
    "in_reply_to_user_id": "2032066678822260736",
    "lang": "zh",
    "note_tweet": {
      "entities": {}
    },
    "possibly_sensitive": false,
    "public_metrics": {
      "bookmark_count": 0,
      "impression_count": 0,
      "like_count": 0,
      "quote_count": 0,
      "reply_count": 0,
      "retweet_count": 0
    },
    "referenced_tweets": [
      {
        "id": "2033558959454670990",
        "type": "replied_to"
      }
    ],
    "reply_settings": "everyone",
    "text": "@redeemkkk 竟然吃这对吗"
  },
  "includes": {
    "media": [
      {
        "height": 1830,
        "media_key": "3_2033558937300353024",
        "public_metrics": {},
        "type": "photo",
        "url": "https://pbs.twimg.com/media/HDinFEebwAAj0y0.jpg",
        "width": 1280
      },
      {
        "height": 1830,
        "media_key": "3_2033558937325502464",
        "public_metrics": {},
        "type": "photo",
        "url": "https://pbs.twimg.com/media/HDinFEkbgAA_17V.jpg",
        "width": 1280
      },
      {
        "height": 1830,
        "media_key": "3_2033558935786160128",
        "public_metrics": {},
        "type": "photo",
        "url": "https://pbs.twimg.com/media/HDinE-1bAAA-w2S.jpg",
        "width": 1280
      },
      {
        "height": 1830,
        "media_key": "3_2033558936297799680",
        "public_metrics": {},
        "type": "photo",
        "url": "https://pbs.twimg.com/media/HDinFAvaAAAOKBO.jpg",
        "width": 1280
      }
    ],
    "tweets": [
      {
        "article": {},
        "attachments": {},
        "author_id": "1722693102367039488",
        "conversation_id": "2033558959454670990",
        "created_at": "2026-03-16T15:05:11.000Z",
        "edit_controls": {
          "editable_until": "2026-03-16T16:05:11.000Z",
          "edits_remaining": 5,
          "is_edit_eligible": false
        },
        "edit_history_tweet_ids": [
          "2033560213702496369"
        ],
        "entities": {
          "mentions": [
            {
              "end": 10,
              "id": "2032066678822260736",
              "start": 0,
              "username": "redeemkkk"
            }
          ]
        },
        "geo": {},
        "id": "2033560213702496369",
        "in_reply_to_user_id": "2032066678822260736",
        "lang": "zh",
        "note_tweet": {
          "entities": {}
        },
        "possibly_sensitive": false,
        "public_metrics": {
          "bookmark_count": 0,
          "impression_count": 0,
          "like_count": 0,
          "quote_count": 0,
          "reply_count": 0,
          "retweet_count": 0
        },
        "referenced_tweets": [
          {
            "id": "2033558959454670990",
            "type": "replied_to"
          }
        ],
        "reply_settings": "everyone",
        "text": "@redeemkkk 竟然吃这对吗"
      },
      {
        "article": {},
        "attachments": {
          "media_keys": [
            "3_2033558937300353024",
            "3_2033558937325502464",
            "3_2033558935786160128",
            "3_2033558936297799680"
          ]
        },
        "author_id": "2032066678822260736",
        "conversation_id": "2033558959454670990",
        "created_at": "2026-03-16T15:00:12.000Z",
        "edit_controls": {
          "editable_until": "2026-03-16T16:00:12.000Z",
          "edits_remaining": 5,
          "is_edit_eligible": true
        },
        "edit_history_tweet_ids": [
          "2033558959454670990"
        ],
        "entities": {
          "urls": [
            {
              "display_url": "pic.x.com/yK0UjGtmTS",
              "end": 29,
              "expanded_url": "https://x.com/redeemkkk/status/2033558959454670990/photo/1",
              "media_key": "3_2033558937300353024",
              "start": 6,
              "url": "https://t.co/yK0UjGtmTS"
            },
            {
              "display_url": "pic.x.com/yK0UjGtmTS",
              "end": 29,
              "expanded_url": "https://x.com/redeemkkk/status/2033558959454670990/photo/1",
              "media_key": "3_2033558937325502464",
              "start": 6,
              "url": "https://t.co/yK0UjGtmTS"
            },
            {
              "display_url": "pic.x.com/yK0UjGtmTS",
              "end": 29,
              "expanded_url": "https://x.com/redeemkkk/status/2033558959454670990/photo/1",
              "media_key": "3_2033558935786160128",
              "start": 6,
              "url": "https://t.co/yK0UjGtmTS"
            },
            {
              "display_url": "pic.x.com/yK0UjGtmTS",
              "end": 29,
              "expanded_url": "https://x.com/redeemkkk/status/2033558959454670990/photo/1",
              "media_key": "3_2033558936297799680",
              "start": 6,
              "url": "https://t.co/yK0UjGtmTS"
            }
          ]
        },
        "geo": {},
        "id": "2033558959454670990",
        "lang": "zh",
        "note_tweet": {
          "entities": {}
        },
        "possibly_sensitive": false,
        "public_metrics": {
          "bookmark_count": 0,
          "impression_count": 0,
          "like_count": 1,
          "quote_count": 0,
          "reply_count": 1,
          "retweet_count": 0
        },
        "reply_settings": "everyone",
        "text": "依旧吃饱饭 https://t.co/yK0UjGtmTS"
      }
    ],
    "users": [
      {
        "created_at": "2023-11-09T19:10:42.000Z",
        "description": "我的生命也能如烟花般绚烂吗 |00年INFJ|跟我互关聊天扩列的话我会很高兴",
        "id": "1722693102367039488",
        "name": "空恋",
        "pinned_tweet_id": "1967745547328205092",
        "profile_image_url": "https://pbs.twimg.com/profile_images/1870808614358966272/yjU8OVI2_normal.jpg",
        "protected": false,
        "public_metrics": {
          "followers_count": 53,
          "following_count": 32,
          "like_count": 180,
          "listed_count": 0,
          "media_count": 2,
          "tweet_count": 129
        },
        "username": "kong_lian53017",
        "verified": false
      },
      {
        "created_at": "2026-03-12T12:10:49.000Z",
        "description": "垃圾桶🗑️",
        "id": "2032066678822260736",
        "name": "kkk",
        "profile_image_url": "https://pbs.twimg.com/profile_images/2033071815753609219/ArBPG9Qt_normal.jpg",
        "protected": false,
        "public_metrics": {
          "followers_count": 1,
          "following_count": 14,
          "like_count": 10,
          "listed_count": 0,
          "media_count": 5,
          "tweet_count": 8
        },
        "username": "redeemkkk",
        "verified": false
      }
    ]
  }
}