{
  "data": {
    "article": {},
    "attachments": {},
    "author_id": "1722693102367039488",
    "conversation_id": "2046291582761197686",
    "created_at": "2026-04-21T04:28:38.000Z",
    "edit_controls": {
      "editable_until": "2026-04-21T05:28:38.000Z",
      "edits_remaining": 5,
      "is_edit_eligible": false
    },
    "edit_history_tweet_ids": [
      "2046445982863511888"
    ],
    "entities": {
      "mentions": [
        {
          "end": 10,
          "id": "2002701945036009474",
          "start": 0,
          "username": "Checkdd3n"
        }
      ]
    },
    "geo": {},
    "id": "2046445982863511888",
    "in_reply_to_user_id": "2002701945036009474",
    "lang": "ja",
    "note_tweet": {
      "entities": {}
    },
    "possibly_sensitive": false,
    "public_metrics": {
      "bookmark_count": 0,
      "impression_count": 0,
      "like_count": 0,
      "quote_count": 0,
      "reply_count": 0,
      "retweet_count": 0
    },
    "referenced_tweets": [
      {
        "id": "2046445563798045129",
        "type": "replied_to"
      }
    ],
    "reply_settings": "everyone",
    "text": "@Checkdd3n 好耶！我也想去山东看海😌大美河南欢迎你！"
  },
  "includes": {
    "tweets": [
      {
        "article": {},
        "attachments": {},
        "author_id": "1722693102367039488",
        "conversation_id": "2046291582761197686",
        "created_at": "2026-04-21T04:28:38.000Z",
        "edit_controls": {
          "editable_until": "2026-04-21T05:28:38.000Z",
          "edits_remaining": 5,
          "is_edit_eligible": false
        },
        "edit_history_tweet_ids": [
          "2046445982863511888"
        ],
        "entities": {
          "mentions": [
            {
              "end": 10,
              "id": "2002701945036009474",
              "start": 0,
              "username": "Checkdd3n"
            }
          ]
        },
        "geo": {},
        "id": "2046445982863511888",
        "in_reply_to_user_id": "2002701945036009474",
        "lang": "ja",
        "note_tweet": {
          "entities": {}
        },
        "possibly_sensitive": false,
        "public_metrics": {
          "bookmark_count": 0,
          "impression_count": 0,
          "like_count": 0,
          "quote_count": 0,
          "reply_count": 0,
          "retweet_count": 0
        },
        "referenced_tweets": [
          {
            "id": "2046445563798045129",
            "type": "replied_to"
          }
        ],
        "reply_settings": "everyone",
        "text": "@Checkdd3n 好耶！我也想去山东看海😌大美河南欢迎你！"
      },
      {
        "article": {},
        "attachments": {},
        "author_id": "2002701945036009474",
        "conversation_id": "2046291582761197686",
        "created_at": "2026-04-21T04:26:58.000Z",
        "edit_controls": {
          "editable_until": "2026-04-21T05:26:58.000Z",
          "edits_remaining": 5,
          "is_edit_eligible": false
        },
        "edit_history_tweet_ids": [
          "2046445563798045129"
        ],
        "entities": {
          "mentions": [
            {
              "end": 15,
              "id": "1722693102367039488",
              "start": 0,
              "username": "kong_lian53017"
            }
          ]
        },
        "geo": {},
        "id": "2046445563798045129",
        "in_reply_to_user_id": "1722693102367039488",
        "lang": "zh",
        "note_tweet": {
          "entities": {}
        },
        "possibly_sensitive": false,
        "public_metrics": {
          "bookmark_count": 0,
          "impression_count": 2,
          "like_count": 1,
          "quote_count": 0,
          "reply_count": 1,
          "retweet_count": 0
        },
        "referenced_tweets": [
          {
            "id": "2046445233442045972",
            "type": "replied_to"
          }
        ],
        "reply_settings": "everyone",
        "text": "@kong_lian53017 不过我要存钱去海南度假山东看海还有河南爬老君山！"
      }
    ],
    "users": [
      {
        "created_at": "2023-11-09T19:10:42.000Z",
        "description": "我的生命也能如烟花般绚烂吗｜00年INFJ｜主页充斥无意义日常碎碎念｜精神状态不稳定间歇性发疯｜会查主页，互fo随缘",
        "id": "1722693102367039488",
        "location": "一颗星",
        "name": "空恋",
        "pinned_tweet_id": "2036676205458632900",
        "profile_image_url": "https://pbs.twimg.com/profile_images/1870808614358966272/yjU8OVI2_normal.jpg",
        "protected": false,
        "public_metrics": {
          "followers_count": 231,
          "following_count": 97,
          "like_count": 8025,
          "listed_count": 0,
          "media_count": 37,
          "tweet_count": 3391
        },
        "username": "kong_lian53017",
        "verified": false
      },
      {
        "created_at": "2025-12-21T11:25:44.000Z",
        "description": "好玩太好玩了，这里。",
        "id": "2002701945036009474",
        "name": "Check",
        "profile_image_url": "https://pbs.twimg.com/profile_images/2046366608608960512/TVNqAl1f_normal.jpg",
        "protected": false,
        "public_metrics": {
          "followers_count": 7,
          "following_count": 124,
          "like_count": 232,
          "listed_count": 0,
          "media_count": 6,
          "tweet_count": 149
        },
        "username": "Checkdd3n",
        "verified": false
      }
    ]
  }
}