{
  "data": {
    "article": {},
    "attachments": {},
    "author_id": "1722693102367039488",
    "conversation_id": "2048714156724060415",
    "created_at": "2026-04-27T10:41:32.000Z",
    "edit_controls": {
      "editable_until": "2026-04-27T11:41:32.000Z",
      "edits_remaining": 5,
      "is_edit_eligible": true
    },
    "edit_history_tweet_ids": [
      "2048714156724060415"
    ],
    "entities": {
      "urls": [
        {
          "display_url": "x.com/Chu_Echooo/sta…",
          "end": 29,
          "expanded_url": "https://twitter.com/Chu_Echooo/status/2048708002136625623",
          "start": 6,
          "url": "https://t.co/vJMgKE4aWL"
        }
      ]
    },
    "geo": {},
    "id": "2048714156724060415",
    "lang": "zh",
    "note_tweet": {
      "entities": {}
    },
    "possibly_sensitive": false,
    "public_metrics": {
      "bookmark_count": 0,
      "impression_count": 0,
      "like_count": 0,
      "quote_count": 0,
      "reply_count": 0,
      "retweet_count": 0
    },
    "referenced_tweets": [
      {
        "id": "2048708002136625623",
        "type": "quoted"
      }
    ],
    "reply_settings": "everyone",
    "text": "便宜你们了 https://t.co/vJMgKE4aWL"
  },
  "includes": {
    "tweets": [
      {
        "article": {},
        "attachments": {},
        "author_id": "1722693102367039488",
        "conversation_id": "2048714156724060415",
        "created_at": "2026-04-27T10:41:32.000Z",
        "edit_controls": {
          "editable_until": "2026-04-27T11:41:32.000Z",
          "edits_remaining": 5,
          "is_edit_eligible": true
        },
        "edit_history_tweet_ids": [
          "2048714156724060415"
        ],
        "entities": {
          "urls": [
            {
              "display_url": "x.com/Chu_Echooo/sta…",
              "end": 29,
              "expanded_url": "https://twitter.com/Chu_Echooo/status/2048708002136625623",
              "start": 6,
              "url": "https://t.co/vJMgKE4aWL"
            }
          ]
        },
        "geo": {},
        "id": "2048714156724060415",
        "lang": "zh",
        "note_tweet": {
          "entities": {}
        },
        "possibly_sensitive": false,
        "public_metrics": {
          "bookmark_count": 0,
          "impression_count": 0,
          "like_count": 0,
          "quote_count": 0,
          "reply_count": 0,
          "retweet_count": 0
        },
        "referenced_tweets": [
          {
            "id": "2048708002136625623",
            "type": "quoted"
          }
        ],
        "reply_settings": "everyone",
        "text": "便宜你们了 https://t.co/vJMgKE4aWL"
      },
      {
        "article": {},
        "attachments": {},
        "author_id": "2033228136180219904",
        "conversation_id": "2048708002136625623",
        "created_at": "2026-04-27T10:17:05.000Z",
        "edit_controls": {
          "editable_until": "2026-04-27T11:17:05.000Z",
          "edits_remaining": 5,
          "is_edit_eligible": true
        },
        "edit_history_tweet_ids": [
          "2048708002136625623"
        ],
        "entities": {},
        "geo": {},
        "id": "2048708002136625623",
        "lang": "zh",
        "note_tweet": {
          "entities": {}
        },
        "possibly_sensitive": false,
        "public_metrics": {
          "bookmark_count": 0,
          "impression_count": 28,
          "like_count": 7,
          "quote_count": 1,
          "reply_count": 1,
          "retweet_count": 0
        },
        "reply_settings": "everyone",
        "text": "我突然觉得我好像在跟大家谈恋爱一样，看见什么想到什么都要说一下。\nMD，便宜你们了。"
      }
    ],
    "users": [
      {
        "created_at": "2023-11-09T19:10:42.000Z",
        "description": "我的生命也能如烟花般绚烂吗｜00年INFJ｜主页充斥无意义日常碎碎念｜精神状态不稳定间歇性发疯｜会查主页，互fo请私信我，随缘互｜匿名：https://t.co/OkTldu1tmL",
        "entities": {
          "description": {
            "urls": [
              {
                "display_url": "ngl.link/kong_lian",
                "end": 91,
                "expanded_url": "https://ngl.link/kong_lian",
                "start": 68,
                "url": "https://t.co/OkTldu1tmL"
              }
            ]
          }
        },
        "id": "1722693102367039488",
        "location": "一颗星",
        "name": "空恋",
        "pinned_tweet_id": "2036676205458632900",
        "profile_image_url": "https://pbs.twimg.com/profile_images/1870808614358966272/yjU8OVI2_normal.jpg",
        "protected": false,
        "public_metrics": {
          "followers_count": 257,
          "following_count": 100,
          "like_count": 10371,
          "listed_count": 0,
          "media_count": 71,
          "tweet_count": 4381
        },
        "username": "kong_lian53017",
        "verified": false
      },
      {
        "created_at": "2026-03-15T17:05:53.000Z",
        "description": "猫叫楚点点/楚娇娇已回喵星/超爱删帖/间歇性人格分裂/不定时轰炸互关/不看也不回陌生人私信介意请取关/嫌我话多可以随意单取",
        "id": "2033228136180219904",
        "location": "电饭煲",
        "name": "阿楚",
        "pinned_tweet_id": "2034935138455609563",
        "profile_image_url": "https://pbs.twimg.com/profile_images/2033228351348019200/RQ5jAlv1_normal.jpg",
        "protected": false,
        "public_metrics": {
          "followers_count": 128,
          "following_count": 65,
          "like_count": 2898,
          "listed_count": 0,
          "media_count": 92,
          "tweet_count": 622
        },
        "username": "Chu_Echooo",
        "verified": false
      }
    ]
  }
}