{
  "data": {
    "article": {},
    "attachments": {},
    "author_id": "1722693102367039488",
    "conversation_id": "2044788503544995952",
    "created_at": "2026-04-16T15:00:49.000Z",
    "edit_controls": {
      "editable_until": "2026-04-16T16:00:49.000Z",
      "edits_remaining": 5,
      "is_edit_eligible": false
    },
    "edit_history_tweet_ids": [
      "2044793140578824553"
    ],
    "entities": {
      "mentions": [
        {
          "end": 13,
          "id": "1604168045424914433",
          "start": 0,
          "username": "bobi01604691"
        }
      ]
    },
    "geo": {},
    "id": "2044793140578824553",
    "in_reply_to_user_id": "1604168045424914433",
    "lang": "ja",
    "note_tweet": {
      "entities": {}
    },
    "possibly_sensitive": false,
    "public_metrics": {
      "bookmark_count": 0,
      "impression_count": 0,
      "like_count": 0,
      "quote_count": 0,
      "reply_count": 0,
      "retweet_count": 0
    },
    "referenced_tweets": [
      {
        "id": "2044792924224049476",
        "type": "replied_to"
      }
    ],
    "reply_settings": "everyone",
    "text": "@bobi01604691 啥叫又。何意味。"
  },
  "includes": {
    "tweets": [
      {
        "article": {},
        "attachments": {},
        "author_id": "1722693102367039488",
        "conversation_id": "2044788503544995952",
        "created_at": "2026-04-16T15:00:49.000Z",
        "edit_controls": {
          "editable_until": "2026-04-16T16:00:49.000Z",
          "edits_remaining": 5,
          "is_edit_eligible": false
        },
        "edit_history_tweet_ids": [
          "2044793140578824553"
        ],
        "entities": {
          "mentions": [
            {
              "end": 13,
              "id": "1604168045424914433",
              "start": 0,
              "username": "bobi01604691"
            }
          ]
        },
        "geo": {},
        "id": "2044793140578824553",
        "in_reply_to_user_id": "1604168045424914433",
        "lang": "ja",
        "note_tweet": {
          "entities": {}
        },
        "possibly_sensitive": false,
        "public_metrics": {
          "bookmark_count": 0,
          "impression_count": 0,
          "like_count": 0,
          "quote_count": 0,
          "reply_count": 0,
          "retweet_count": 0
        },
        "referenced_tweets": [
          {
            "id": "2044792924224049476",
            "type": "replied_to"
          }
        ],
        "reply_settings": "everyone",
        "text": "@bobi01604691 啥叫又。何意味。"
      },
      {
        "article": {},
        "attachments": {},
        "author_id": "1604168045424914433",
        "conversation_id": "2044788503544995952",
        "created_at": "2026-04-16T14:59:58.000Z",
        "edit_controls": {
          "editable_until": "2026-04-16T15:59:58.000Z",
          "edits_remaining": 5,
          "is_edit_eligible": false
        },
        "edit_history_tweet_ids": [
          "2044792924224049476"
        ],
        "entities": {
          "mentions": [
            {
              "end": 15,
              "id": "1722693102367039488",
              "start": 0,
              "username": "kong_lian53017"
            }
          ]
        },
        "geo": {},
        "id": "2044792924224049476",
        "in_reply_to_user_id": "1722693102367039488",
        "lang": "zh",
        "note_tweet": {
          "entities": {}
        },
        "possibly_sensitive": false,
        "public_metrics": {
          "bookmark_count": 0,
          "impression_count": 2,
          "like_count": 0,
          "quote_count": 0,
          "reply_count": 1,
          "retweet_count": 0
        },
        "referenced_tweets": [
          {
            "id": "2044788503544995952",
            "type": "replied_to"
          }
        ],
        "reply_settings": "everyone",
        "text": "@kong_lian53017 又有男人表现差了吗"
      }
    ],
    "users": [
      {
        "created_at": "2023-11-09T19:10:42.000Z",
        "description": "我的生命也能如烟花般绚烂吗｜00年INFJ｜主页充斥无意义日常碎碎念｜精神状态不稳定间歇性发疯｜会查主页，互fo随缘",
        "id": "1722693102367039488",
        "location": "一颗星",
        "name": "空恋",
        "pinned_tweet_id": "2036676205458632900",
        "profile_image_url": "https://pbs.twimg.com/profile_images/1870808614358966272/yjU8OVI2_normal.jpg",
        "protected": false,
        "public_metrics": {
          "followers_count": 189,
          "following_count": 91,
          "like_count": 6135,
          "listed_count": 0,
          "media_count": 31,
          "tweet_count": 2654
        },
        "username": "kong_lian53017",
        "verified": false
      },
      {
        "created_at": "2022-12-17T17:34:08.000Z",
        "description": "前看天辽地阔",
        "id": "1604168045424914433",
        "name": "萧余丶",
        "pinned_tweet_id": "2042899134324314543",
        "profile_image_url": "https://pbs.twimg.com/profile_images/2042995631342653440/bYlacDFD_normal.jpg",
        "protected": false,
        "public_metrics": {
          "followers_count": 48,
          "following_count": 147,
          "like_count": 2518,
          "listed_count": 1,
          "media_count": 24,
          "tweet_count": 767
        },
        "username": "bobi01604691",
        "verified": false
      }
    ]
  }
}